{
    "label": "Pride - In the Name of Love",
    "description": "Pride Month - June 2021",
    "list": 
  [
{
"label":"The art of being normal",
"isbns": [
"9780374302375"
]
},
{
"label":"Be Dazzled",
"isbns": [
"9781492682691",
"9781492682707",
"9781492682707"
]
},
{
"label":"Beyond magenta : transgender teens speak out",
"isbns": [
"9780763656119",
"9780763670351",
"9780763670351"
]
},
{
"label":"Brave face : a memoir",
"isbns": [
"9781534431515"
]
},
{
"label":"Can't Take That Away",
"isbns": [
"9781547605309",
"9781547605316"
]
},
{
"label":"Detransition, baby : a novel",
"isbns": [
"9780593133392",
"9780593133378"
]
},
{
"label":"A fountain filled with blood",
"isbns": [
"9780312304102",
"9780792733164",
"9781250007827"
]
},
{
"label":"The gender quest workbook : a guide for teens & young adults exploring gender identity",
"isbns": [
"9781626252974"
]
},
{
"label":"GLBTQ : the survival guide for gay, lesbian, bisexual, transgender, and questioning teens",
"isbns": [
"9781575423630"
]
},
{
"label":"GLBTQ : the survival guide for queer & questioning teens",
"isbns": [
"9781575421261"
]
},
{
"label":"The hazards of love. Book 1, Bright world",
"isbns": [
"9781620108574"
]
},
{
"label":"The henna wars",
"isbns": [
"9781624149689",
"9780593216569"
]
},
{
"label":"Honey Girl",
"isbns": [
"9780778311027",
"9781488077500",
"9781488077500"
]
},
{
"label":"It gets better : coming out, overcoming bullying, and creating a life worth living",
"isbns": [
"9780525952336",
"9781455113378",
"9780452297616"
]
},
{
"label":"Last Night at the Telegraph Club",
"isbns": [
"9780525555254",
"9780593341650",
"9780525555261"
]
},
{
"label":"Less : a novel",
"isbns": [
"9780316465182",
"9780316316132",
"9781549118715",
"9780316316125",
"9780316465182",
"9781478966296"
]
},
{
"label":"LGBTQ+ athletes claim the field : striving for equality",
"isbns": [
"9781467780124"
]
},
{
"label":"Lily and the octopus",
"isbns": [
"9781442399624",
"9781501126222",
"9781410490834",
"9781508217923",
"9781509412198",
"9781501126239"
]
},
{
"label":"A little life : a novel",
"isbns": [
"9780385539265",
"9780385539265",
"9780385539258"
]
},
{
"label":"Openly straight",
"isbns": [
"9780545509893"
]
},
{
"label":"Out! : how to be your authentic self",
"isbns": [
"9781419739941"
]
},
{
"label":"Plain Bad Heroines",
"isbns": [
"9780062942883",
"9780062942876",
"9780062942876",
"9780062942852"
]
},
{
"label":"Pride : the celebration and the struggle",
"isbns": [
"9781459821248"
]
},
{
"label":"Queer : the ultimate LGBTQ guide for teens",
"isbns": [
"9781541578586",
"9781541578593"
]
},
{
"label":"Red, white & royal blue : a novel",
"isbns": [
"9781250316776",
"9781250233950",
"9781250316783"
]
},
{
"label":"Some assembly required : the not-so-secret life of a transgender teen",
"isbns": [
"9781481416757"
]
},
{
"label":"Something to talk about",
"isbns": [
"9780593102534",
"9780593214473",
"9780593102527",
"9780593102534"
]
},
{
"label":"Speak No Evil",
"isbns": [
"9780062199096",
"9780061284922"
]
},
{
"label":"This is how it always is",
"isbns": [
"9781250088550",
"9781250118523",
"9781427282538"
]
},
{
"label":"Trans teen survival guide",
"isbns": [
"9781785923418"
]
},
{
"label":"Trans+ : love, sex, romance, and being you",
"isbns": [
"9781433829833"
]
},
{
"label":"We Contain Multitudes",
"isbns": [
"9781549124976",
"9780316424110",
"9780316524650"
]
}
]
}